{
	"configurations" : 
	[
		{
			"directories" : 
			[
				{
					"build" : ".",
					"childIndexes" : 
					[
						1
					],
					"hasInstallRule" : true,
					"minimumCMakeVersion" : 
					{
						"string" : "3.5"
					},
					"projectIndex" : 0,
					"source" : ".",
					"targetIndexes" : 
					[
						4,
						5,
						6,
						7,
						8,
						9,
						10,
						11,
						12,
						13,
						14,
						15,
						16,
						17,
						18,
						19
					]
				},
				{
					"build" : "gtest",
					"minimumCMakeVersion" : 
					{
						"string" : "2.8.12"
					},
					"parentIndex" : 0,
					"projectIndex" : 1,
					"source" : "/opt/ros/foxy/src/gtest_vendor",
					"targetIndexes" : 
					[
						0,
						1,
						2,
						3
					]
				}
			],
			"name" : "Release",
			"projects" : 
			[
				{
					"childIndexes" : 
					[
						1
					],
					"directoryIndexes" : 
					[
						0
					],
					"name" : "rviz_visual_tools",
					"targetIndexes" : 
					[
						4,
						5,
						6,
						7,
						8,
						9,
						10,
						11,
						12,
						13,
						14,
						15,
						16,
						17,
						18,
						19
					]
				},
				{
					"directoryIndexes" : 
					[
						1
					],
					"name" : "gtest",
					"parentIndex" : 0,
					"targetIndexes" : 
					[
						0,
						1,
						2,
						3
					]
				}
			],
			"targets" : 
			[
				{
					"directoryIndex" : 1,
					"id" : "gtest::@0af4add9fe94340e763e",
					"jsonFile" : "target-gtest-Release-d93b1e0f1e4aff2acb24.json",
					"name" : "gtest",
					"projectIndex" : 1
				},
				{
					"directoryIndex" : 1,
					"id" : "gtest_autogen::@0af4add9fe94340e763e",
					"jsonFile" : "target-gtest_autogen-Release-1d36ffa3ca6180ab2fcc.json",
					"name" : "gtest_autogen",
					"projectIndex" : 1
				},
				{
					"directoryIndex" : 1,
					"id" : "gtest_main::@0af4add9fe94340e763e",
					"jsonFile" : "target-gtest_main-Release-720fd1e560e7d12d088b.json",
					"name" : "gtest_main",
					"projectIndex" : 1
				},
				{
					"directoryIndex" : 1,
					"id" : "gtest_main_autogen::@0af4add9fe94340e763e",
					"jsonFile" : "target-gtest_main_autogen-Release-05095e06e57bd0c499b0.json",
					"name" : "gtest_main_autogen",
					"projectIndex" : 1
				},
				{
					"directoryIndex" : 0,
					"id" : "rviz_visual_tools::@6890427a1f51a3e7e1df",
					"jsonFile" : "target-rviz_visual_tools-Release-a9ff9f7acfd5c11dbcab.json",
					"name" : "rviz_visual_tools",
					"projectIndex" : 0
				},
				{
					"directoryIndex" : 0,
					"id" : "rviz_visual_tools_autogen::@6890427a1f51a3e7e1df",
					"jsonFile" : "target-rviz_visual_tools_autogen-Release-ce1c5a3b029e1707d57f.json",
					"name" : "rviz_visual_tools_autogen",
					"projectIndex" : 0
				},
				{
					"directoryIndex" : 0,
					"id" : "rviz_visual_tools_demo::@6890427a1f51a3e7e1df",
					"jsonFile" : "target-rviz_visual_tools_demo-Release-9ad36061d411a89a0967.json",
					"name" : "rviz_visual_tools_demo",
					"projectIndex" : 0
				},
				{
					"directoryIndex" : 0,
					"id" : "rviz_visual_tools_demo_autogen::@6890427a1f51a3e7e1df",
					"jsonFile" : "target-rviz_visual_tools_demo_autogen-Release-156345227ed2e94f724d.json",
					"name" : "rviz_visual_tools_demo_autogen",
					"projectIndex" : 0
				},
				{
					"directoryIndex" : 0,
					"id" : "rviz_visual_tools_gui::@6890427a1f51a3e7e1df",
					"jsonFile" : "target-rviz_visual_tools_gui-Release-6dacaea3852dab9891d8.json",
					"name" : "rviz_visual_tools_gui",
					"projectIndex" : 0
				},
				{
					"directoryIndex" : 0,
					"id" : "rviz_visual_tools_gui_autogen::@6890427a1f51a3e7e1df",
					"jsonFile" : "target-rviz_visual_tools_gui_autogen-Release-c0f91b982e5ecec58fb5.json",
					"name" : "rviz_visual_tools_gui_autogen",
					"projectIndex" : 0
				},
				{
					"directoryIndex" : 0,
					"id" : "rviz_visual_tools_imarker_simple::@6890427a1f51a3e7e1df",
					"jsonFile" : "target-rviz_visual_tools_imarker_simple-Release-cc3e3a4e1ce19ceeadf4.json",
					"name" : "rviz_visual_tools_imarker_simple",
					"projectIndex" : 0
				},
				{
					"directoryIndex" : 0,
					"id" : "rviz_visual_tools_imarker_simple_autogen::@6890427a1f51a3e7e1df",
					"jsonFile" : "target-rviz_visual_tools_imarker_simple_autogen-Release-54218e8f0adbbba7993e.json",
					"name" : "rviz_visual_tools_imarker_simple_autogen",
					"projectIndex" : 0
				},
				{
					"directoryIndex" : 0,
					"id" : "rviz_visual_tools_imarker_simple_demo::@6890427a1f51a3e7e1df",
					"jsonFile" : "target-rviz_visual_tools_imarker_simple_demo-Release-f6f8c7a621af33ecc7d9.json",
					"name" : "rviz_visual_tools_imarker_simple_demo",
					"projectIndex" : 0
				},
				{
					"directoryIndex" : 0,
					"id" : "rviz_visual_tools_imarker_simple_demo_autogen::@6890427a1f51a3e7e1df",
					"jsonFile" : "target-rviz_visual_tools_imarker_simple_demo_autogen-Release-d93c7e2467fad8307d99.json",
					"name" : "rviz_visual_tools_imarker_simple_demo_autogen",
					"projectIndex" : 0
				},
				{
					"directoryIndex" : 0,
					"id" : "rviz_visual_tools_remote_control::@6890427a1f51a3e7e1df",
					"jsonFile" : "target-rviz_visual_tools_remote_control-Release-c62c61454a4325c5a1f7.json",
					"name" : "rviz_visual_tools_remote_control",
					"projectIndex" : 0
				},
				{
					"directoryIndex" : 0,
					"id" : "rviz_visual_tools_remote_control_autogen::@6890427a1f51a3e7e1df",
					"jsonFile" : "target-rviz_visual_tools_remote_control_autogen-Release-bab8b5cc211fb76c7130.json",
					"name" : "rviz_visual_tools_remote_control_autogen",
					"projectIndex" : 0
				},
				{
					"directoryIndex" : 0,
					"id" : "rviz_visual_tools_rvt_test::@6890427a1f51a3e7e1df",
					"jsonFile" : "target-rviz_visual_tools_rvt_test-Release-eae4806c87a0abf5996e.json",
					"name" : "rviz_visual_tools_rvt_test",
					"projectIndex" : 0
				},
				{
					"directoryIndex" : 0,
					"id" : "rviz_visual_tools_rvt_test_autogen::@6890427a1f51a3e7e1df",
					"jsonFile" : "target-rviz_visual_tools_rvt_test_autogen-Release-a60791bd1457b93dc2e6.json",
					"name" : "rviz_visual_tools_rvt_test_autogen",
					"projectIndex" : 0
				},
				{
					"directoryIndex" : 0,
					"id" : "rviz_visual_tools_uninstall::@6890427a1f51a3e7e1df",
					"jsonFile" : "target-rviz_visual_tools_uninstall-Release-148ce60071b8a77c6533.json",
					"name" : "rviz_visual_tools_uninstall",
					"projectIndex" : 0
				},
				{
					"directoryIndex" : 0,
					"id" : "uninstall::@6890427a1f51a3e7e1df",
					"jsonFile" : "target-uninstall-Release-9a0ff07bb078e199056a.json",
					"name" : "uninstall",
					"projectIndex" : 0
				}
			]
		}
	],
	"kind" : "codemodel",
	"paths" : 
	{
		"build" : "/home/mu/IVG/ws_moveit/build/rviz_visual_tools",
		"source" : "/home/mu/IVG/ws_moveit/src/rviz_visual_tools"
	},
	"version" : 
	{
		"major" : 2,
		"minor" : 0
	}
}
